Workbook

Sheet README
A1: RBL Bank — Book Growth Analysis (BBRL liabilities): page-wise metric extraction
A2: Source: 01_Book_Growth_Analysis.pdf (1 page, 2 data blocks) | ₹ Cr | MEB = month-end balance, MAB = monthly average balance
A3: ⚠ DRAFT ONLY — Requires review and approval by a qualified Alvarez and Marsal professional before use.
A5: Sheet map
A6: B1_MEB_Periods | B6: Block 1 — MEB by product × customer segment for CM, LY, LM, LQ, with printed growth tables and sign checks
A7: B1_Metrics | B7: Notation + exhaustive metrics for Block 1
A8: B2_Balance_Movement | B8: Block 2 — Balance Movement: MAB by segment × product across CD, PD, CM, LM, LY, LYCM and the < ₹3 Cr / Individual < ₹3 Cr sub-books
A9: B2_Metrics | B9: Notation + exhaustive metrics for Block 2
A11: Colour legend
A12: Blue text | B12: Hard-coded input transcribed from the PDF
A13: Blue italic on grey | B13: Budget / projected value (ᴾ) transcribed from the PDF
A14: Black text | B14: Formula on the same sheet
A15: Green text | B15: Link to another sheet
A16: Yellow fill | B16: Data flag to review
A18: Key assumptions (confirm with client)
A19: 1 | B19: Printed growth % and 'Growth in Allocated Segment' are signed in the PDF (e.g. MASS CA CM vs LY = −49.12%) and tie to recomputed values. 'Growth in Allocated Segment' is the change in segment share, in pp, not a growth rate.
A20: 2 | B20: Filter context: BBB Flag = BBRL, all other filters = All. Report header was not captured; title taken from file name.
A21: 3 | B21: '< 3 Cr' and '< 3 Ind Cr' columns are the sub-book of customers below ₹3 Cr and of individual customers below ₹3 Cr (as printed: 'CM < 3 Cr*'). The < 3 Cr book grew only +8.5% YoY while the ≥ ₹3 Cr remainder grew +114% — growth is large-ticket.
A22: 4 | B22: CD / PD read as current-day / previous-day MAB; CM = current month; LM = last month; LQ = last quarter-end month; LY = last year; LYCM = last-year current-month basis. CM vs LM and CM vs LY diffs on the MAB page tie to LM* and LY* here.
A23: 5 | B23: Cross-page: Balance Movement CD* / CM* grand total (115,448.64) equals the MAB page grand total; Block-1 CM MEB grand total (113,109.81) is a different measure (MEB).
A24: Confidentiality | B24: Client-confidential RBL Bank data.
A26: ⚠ DRAFT ONLY — Requires review and approval by a qualified Alvarez and Marsal professional before use.
A28: CORRECTED INGESTION HANDOFF
A29: All 53 business definitions retain their readable notation and include a parser-safe Executable Formula.
A30: Examples are static audited values so validation does not depend on local Excel recalculation.
A31: Import: ./run.sh business-rules 01_Book_Growth_Analysis_Metrics.xlsx --apply --approved-only

Sheet B1_MEB_Periods
A1: Block 1 — MEB by product × customer segment (CM, LY, LM, LQ)
A2: Source: Book Growth Analysis.pdf | ₹ Cr | month-end balances; all actuals | shares recomputed
A3: ⚠ DRAFT ONLY — Requires review and approval by a qualified Alvarez and Marsal professional before use.
A5: CM MEB
A6: # | B6: Product | C6: INSIGNIA | D6: SIGNATURE | E6: ASPIRE | F6: MASS | G6: Printed total | H6: Σ segments | I6: Gap | J6: Share INSIGNIA | K6: Share SIGNATURE | L6: Share ASPIRE | M6: Share MASS | N6: Product share of GT
A7: 1 | B7: CA | C7: 3849.97 | D7: 438.94 | E7: 515.22 | F7: 1393.38 | G7: 6197.51 | H7: =SUM(C7:F7) | I7: =G7-H7 | J7: =C7/$G7 | K7: =D7/$G7 | L7: =E7/$G7 | M7: =F7/$G7 | N7: =G7/$G$11
A8: 2 | B8: SA | C8: 11257.45 | D8: 3129.55 | E8: 1601 | F8: 3434.88 | G8: 19422.88 | H8: =SUM(C8:F8) | I8: =G8-H8 | J8: =C8/$G8 | K8: =D8/$G8 | L8: =E8/$G8 | M8: =F8/$G8 | N8: =G8/$G$11
A9: 3 | B9: Deposits | C9: 52910.64 | D9: 7509.46 | E9: 6510.42 | F9: 20542.05 | G9: 87472.57 | H9: =SUM(C9:F9) | I9: =G9-H9 | J9: =C9/$G9 | K9: =D9/$G9 | L9: =E9/$G9 | M9: =F9/$G9 | N9: =G9/$G$11
A10: 4 | B10: ODFD | C10: 8.78 | D10: 3.34 | E10: 1.51 | F10: 3.22 | G10: 16.84 | H10: =SUM(C10:F10) | I10: =G10-H10 | J10: =C10/$G10 | K10: =D10/$G10 | L10: =E10/$G10 | M10: =F10/$G10 | N10: =G10/$G$11
A11: 5 | B11: Grand Total (printed) | C11: 68026.83 | D11: 11081.29 | E11: 8628.16 | F11: 25373.53 | G11: 113109.81 | H11: =SUM(C11:F11) | I11: =G11-H11 | J11: =C11/$G11 | K11: =D11/$G11 | L11: =E11/$G11 | M11: =F11/$G11 | N11: =G11/$G$11
B12: Σ products (computed) | C12: =SUM(C7:C10) | D12: =SUM(D7:D10) | E12: =SUM(E7:E10) | F12: =SUM(F7:F10) | G12: =SUM(G7:G10) | H12: =SUM(C12:F12)
B13: Gap: printed GT − Σ products | C13: =C11-C12 | D13: =D11-D12 | E13: =E11-E12 | F13: =F11-F12 | G13: =G11-G12
A14: LY MEB
A15: # | B15: Product | C15: INSIGNIA | D15: SIGNATURE | E15: ASPIRE | F15: MASS | G15: Printed total | H15: Σ segments | I15: Gap | J15: Share INSIGNIA | K15: Share SIGNATURE | L15: Share ASPIRE | M15: Share MASS | N15: Product share of GT
A16: 1 | B16: CA | C16: 4906.99 | D16: 551.97 | E16: 645.42 | F16: 2738.8 | G16: 8843.18 | H16: =SUM(C16:F16) | I16: =G16-H16 | J16: =C16/$G16 | K16: =D16/$G16 | L16: =E16/$G16 | M16: =F16/$G16 | N16: =G16/$G$20
A17: 2 | B17: SA | C17: 11203.79 | D17: 3115.25 | E17: 1566.72 | F17: 3717.23 | G17: 19602.98 | H17: =SUM(C17:F17) | I17: =G17-H17 | J17: =C17/$G17 | K17: =D17/$G17 | L17: =E17/$G17 | M17: =F17/$G17 | N17: =G17/$G$20
A18: 3 | B18: Deposits | C18: 24996.33 | D18: 6013.38 | E18: 5541.37 | F18: 22778.25 | G18: 59329.33 | H18: =SUM(C18:F18) | I18: =G18-H18 | J18: =C18/$G18 | K18: =D18/$G18 | L18: =E18/$G18 | M18: =F18/$G18 | N18: =G18/$G$20
A19: 4 | B19: ODFD | C19: 9 | D19: 4.74 | E19: 1.64 | F19: 3.54 | G19: 18.92 | H19: =SUM(C19:F19) | I19: =G19-H19 | J19: =C19/$G19 | K19: =D19/$G19 | L19: =E19/$G19 | M19: =F19/$G19 | N19: =G19/$G$20
A20: 5 | B20: Grand Total (printed) | C20: 41116.12 | D20: 9685.33 | E20: 7755.15 | F20: 29237.82 | G20: 87794.42 | H20: =SUM(C20:F20) | I20: =G20-H20 | J20: =C20/$G20 | K20: =D20/$G20 | L20: =E20/$G20 | M20: =F20/$G20 | N20: =G20/$G$20
B21: Σ products (computed) | C21: =SUM(C16:C19) | D21: =SUM(D16:D19) | E21: =SUM(E16:E19) | F21: =SUM(F16:F19) | G21: =SUM(G16:G19) | H21: =SUM(C21:F21)
B22: Gap: printed GT − Σ products | C22: =C20-C21 | D22: =D20-D21 | E22: =E20-E21 | F22: =F20-F21 | G22: =G20-G21
A23: LM MEB
A24: # | B24: Product | C24: INSIGNIA | D24: SIGNATURE | E24: ASPIRE | F24: MASS | G24: Printed total | H24: Σ segments | I24: Gap | J24: Share INSIGNIA | K24: Share SIGNATURE | L24: Share ASPIRE | M24: Share MASS | N24: Product share of GT
A25: 1 | B25: CA | C25: 3774.25 | D25: 491.11 | E25: 534.41 | F25: 1638.21 | G25: 6437.98 | H25: =SUM(C25:F25) | I25: =G25-H25 | J25: =C25/$G25 | K25: =D25/$G25 | L25: =E25/$G25 | M25: =F25/$G25 | N25: =G25/$G$29
A26: 2 | B26: SA | C26: 11110.84 | D26: 3152.62 | E26: 1582.89 | F26: 3424.5 | G26: 19270.85 | H26: =SUM(C26:F26) | I26: =G26-H26 | J26: =C26/$G26 | K26: =D26/$G26 | L26: =E26/$G26 | M26: =F26/$G26 | N26: =G26/$G$29
A27: 3 | B27: Deposits | C27: 33926.56 | D27: 6675.19 | E27: 5916 | F27: 21149.29 | G27: 67667.04 | H27: =SUM(C27:F27) | I27: =G27-H27 | J27: =C27/$G27 | K27: =D27/$G27 | L27: =E27/$G27 | M27: =F27/$G27 | N27: =G27/$G$29
A28: 4 | B28: ODFD | C28: 12.81 | D28: 3.45 | E28: 2.71 | F28: 3.56 | G28: 22.52 | H28: =SUM(C28:F28) | I28: =G28-H28 | J28: =C28/$G28 | K28: =D28/$G28 | L28: =E28/$G28 | M28: =F28/$G28 | N28: =G28/$G$29
A29: 5 | B29: Grand Total (printed) | C29: 48824.46 | D29: 10322.37 | E29: 8036.01 | F29: 26215.56 | G29: 93398.4 | H29: =SUM(C29:F29) | I29: =G29-H29 | J29: =C29/$G29 | K29: =D29/$G29 | L29: =E29/$G29 | M29: =F29/$G29 | N29: =G29/$G$29
B30: Σ products (computed) | C30: =SUM(C25:C28) | D30: =SUM(D25:D28) | E30: =SUM(E25:E28) | F30: =SUM(F25:F28) | G30: =SUM(G25:G28) | H30: =SUM(C30:F30)
B31: Gap: printed GT − Σ products | C31: =C29-C30 | D31: =D29-D30 | E31: =E29-E30 | F31: =F29-F30 | G31: =G29-G30
A32: LQ MEB
A33: # | B33: Product | C33: INSIGNIA | D33: SIGNATURE | E33: ASPIRE | F33: MASS | G33: Printed total | H33: Σ segments | I33: Gap | J33: Share INSIGNIA | K33: Share SIGNATURE | L33: Share ASPIRE | M33: Share MASS | N33: Product share of GT
A34: 1 | B34: CA | C34: 3879.65 | D34: 462.67 | E34: 563.06 | F34: 2036.22 | G34: 6941.6 | H34: =SUM(C34:F34) | I34: =G34-H34 | J34: =C34/$G34 | K34: =D34/$G34 | L34: =E34/$G34 | M34: =F34/$G34 | N34: =G34/$G$38
A35: 2 | B35: SA | C35: 11051.02 | D35: 3122.71 | E35: 1621.02 | F35: 3334.89 | G35: 19129.64 | H35: =SUM(C35:F35) | I35: =G35-H35 | J35: =C35/$G35 | K35: =D35/$G35 | L35: =E35/$G35 | M35: =F35/$G35 | N35: =G35/$G$38
A36: 3 | B36: Deposits | C36: 26052.53 | D36: 6330.66 | E36: 5724.89 | F36: 22061.57 | G36: 60169.66 | H36: =SUM(C36:F36) | I36: =G36-H36 | J36: =C36/$G36 | K36: =D36/$G36 | L36: =E36/$G36 | M36: =F36/$G36 | N36: =G36/$G$38
A37: 4 | B37: ODFD | C37: 13.73 | D37: 3.46 | E37: 1.45 | F37: 3.48 | G37: 22.12 | H37: =SUM(C37:F37) | I37: =G37-H37 | J37: =C37/$G37 | K37: =D37/$G37 | L37: =E37/$G37 | M37: =F37/$G37 | N37: =G37/$G$38
A38: 5 | B38: Grand Total (printed) | C38: 40996.93 | D38: 9919.5 | E38: 7910.42 | F38: 27436.17 | G38: 86263.02 | H38: =SUM(C38:F38) | I38: =G38-H38 | J38: =C38/$G38 | K38: =D38/$G38 | L38: =E38/$G38 | M38: =F38/$G38 | N38: =G38/$G$38
B39: Σ products (computed) | C39: =SUM(C34:C37) | D39: =SUM(D34:D37) | E39: =SUM(E34:E37) | F39: =SUM(F34:F37) | G39: =SUM(G34:G37) | H39: =SUM(C39:F39)
B40: Gap: printed GT − Σ products | C40: =C38-C39 | D40: =D38-D39 | E40: =E38-E39 | F40: =F38-F39 | G40: =G38-G39
A42: CM vs LY: computed growth and share shift vs printed (signed as printed)
A43: # | B43: Product | C43: g INSIGNIA | D43: g SIGNATURE | E43: g ASPIRE | F43: g MASS | G43: g Total | H43: Δshare INSIGNIA (pp) | I43: Δshare SIGNATURE (pp) | J43: Δshare ASPIRE (pp) | K43: Δshare MASS (pp) | L43: Printed g INSIGNIA | M43: Printed g SIGNATURE | N43: Printed g ASPIRE | O43: Printed g MASS | P43: Printed g Total | Q43: Printed Δ INSIGNIA | R43: Printed Δ SIGNATURE | S43: Printed Δ ASPIRE | T43: Printed Δ MASS | U43: Max |computed − printed| (growth; shift ÷ 100) | V43: Sign mismatches computed vs printed
A44: 1 | B44: CA | C44: =C7/C16-1 | D44: =D7/D16-1 | E44: =E7/E16-1 | F44: =F7/F16-1 | G44: =G7/G16-1 | H44: =(J7-J16)*100 | I44: =(K7-K16)*100 | J44: =(L7-L16)*100 | K44: =(M7-M16)*100 | L44: -0.2154 | M44: -0.2048 | N44: -0.2017 | O44: -0.4912 | P44: -0.2992 | Q44: 6.63 | R44: 0.84 | S44: 1.01 | T44: -8.49 | U44: =MAX(ABS(C44-L44),ABS(D44-M44),ABS(E44-N44),ABS(F44-O44),ABS(G44-P44),ABS(H44-Q44)/100,ABS(I44-R44)/100,ABS(J44-S44)/100,ABS(K44-T44)/100) | V44: =SUMPRODUCT(--(SIGN(ROUND(C44:G44,4))<>SIGN(ROUND(L44:P44,4))))+SUMPRODUCT(--(SIGN(ROUND(H44:K44,2))<>SIGN(ROUND(Q44:T44,2))))
A45: 2 | B45: SA | C45: =C8/C17-1 | D45: =D8/D17-1 | E45: =E8/E17-1 | F45: =F8/F17-1 | G45: =G8/G17-1 | H45: =(J8-J17)*100 | I45: =(K8-K17)*100 | J45: =(L8-L17)*100 | K45: =(M8-M17)*100 | L45: 0.0048 | M45: 0.0046 | N45: 0.0219 | O45: -0.076 | P45: -0.0092 | Q45: 0.81 | R45: 0.22 | S45: 0.25 | T45: -1.28 | U45: =MAX(ABS(C45-L45),ABS(D45-M45),ABS(E45-N45),ABS(F45-O45),ABS(G45-P45),ABS(H45-Q45)/100,ABS(I45-R45)/100,ABS(J45-S45)/100,ABS(K45-T45)/100) | V45: =SUMPRODUCT(--(SIGN(ROUND(C45:G45,4))<>SIGN(ROUND(L45:P45,4))))+SUMPRODUCT(--(SIGN(ROUND(H45:K45,2))<>SIGN(ROUND(Q45:T45,2))))
A46: 3 | B46: Deposits | C46: =C9/C18-1 | D46: =D9/D18-1 | E46: =E9/E18-1 | F46: =F9/F18-1 | G46: =G9/G18-1 | H46: =(J9-J18)*100 | I46: =(K9-K18)*100 | J46: =(L9-L18)*100 | K46: =(M9-M18)*100 | L46: 1.1167 | M46: 0.2488 | N46: 0.1749 | O46: -0.0982 | P46: 0.4744 | Q46: 18.36 | R46: -1.55 | S46: -1.9 | T46: -14.91 | U46: =MAX(ABS(C46-L46),ABS(D46-M46),ABS(E46-N46),ABS(F46-O46),ABS(G46-P46),ABS(H46-Q46)/100,ABS(I46-R46)/100,ABS(J46-S46)/100,ABS(K46-T46)/100) | V46: =SUMPRODUCT(--(SIGN(ROUND(C46:G46,4))<>SIGN(ROUND(L46:P46,4))))+SUMPRODUCT(--(SIGN(ROUND(H46:K46,2))<>SIGN(ROUND(Q46:T46,2))))
A47: 4 | B47: ODFD | C47: =C10/C19-1 | D47: =D10/D19-1 | E47: =E10/E19-1 | F47: =F10/F19-1 | G47: =G10/G19-1 | H47: =(J10-J19)*100 | I47: =(K10-K19)*100 | J47: =(L10-L19)*100 | K47: =(M10-M19)*100 | L47: -0.0251 | M47: -0.296 | N47: -0.0805 | O47: -0.0904 | P47: -0.1099 | Q47: 4.54 | R47: -5.23 | S47: 0.29 | T47: 0.41 | U47: =MAX(ABS(C47-L47),ABS(D47-M47),ABS(E47-N47),ABS(F47-O47),ABS(G47-P47),ABS(H47-Q47)/100,ABS(I47-R47)/100,ABS(J47-S47)/100,ABS(K47-T47)/100) | V47: =SUMPRODUCT(--(SIGN(ROUND(C47:G47,4))<>SIGN(ROUND(L47:P47,4))))+SUMPRODUCT(--(SIGN(ROUND(H47:K47,2))<>SIGN(ROUND(Q47:T47,2))))
A48: 5 | B48: Grand Total | C48: =C11/C20-1 | D48: =D11/D20-1 | E48: =E11/E20-1 | F48: =F11/F20-1 | G48: =G11/G20-1 | H48: =(J11-J20)*100 | I48: =(K11-K20)*100 | J48: =(L11-L20)*100 | K48: =(M11-M20)*100 | L48: 0.6545 | M48: 0.1441 | N48: 0.1126 | O48: -0.1322 | P48: 0.2883 | Q48: 13.31 | R48: -1.23 | S48: -1.21 | T48: -10.87 | U48: =MAX(ABS(C48-L48),ABS(D48-M48),ABS(E48-N48),ABS(F48-O48),ABS(G48-P48),ABS(H48-Q48)/100,ABS(I48-R48)/100,ABS(J48-S48)/100,ABS(K48-T48)/100) | V48: =SUMPRODUCT(--(SIGN(ROUND(C48:G48,4))<>SIGN(ROUND(L48:P48,4))))+SUMPRODUCT(--(SIGN(ROUND(H48:K48,2))<>SIGN(ROUND(Q48:T48,2))))
A50: CM vs LM: computed growth and share shift vs printed (signed as printed)
A51: # | B51: Product | C51: g INSIGNIA | D51: g SIGNATURE | E51: g ASPIRE | F51: g MASS | G51: g Total | H51: Δshare INSIGNIA (pp) | I51: Δshare SIGNATURE (pp) | J51: Δshare ASPIRE (pp) | K51: Δshare MASS (pp) | L51: Printed g INSIGNIA | M51: Printed g SIGNATURE | N51: Printed g ASPIRE | O51: Printed g MASS | P51: Printed g Total | Q51: Printed Δ INSIGNIA | R51: Printed Δ SIGNATURE | S51: Printed Δ ASPIRE | T51: Printed Δ MASS | U51: Max |computed − printed| (growth; shift ÷ 100) | V51: Sign mismatches computed vs printed
A52: 1 | B52: CA | C52: =C7/C25-1 | D52: =D7/D25-1 | E52: =E7/E25-1 | F52: =F7/F25-1 | G52: =G7/G25-1 | H52: =(J7-J25)*100 | I52: =(K7-K25)*100 | J52: =(L7-L25)*100 | K52: =(M7-M25)*100 | L52: 0.0201 | M52: -0.1062 | N52: -0.0359 | O52: -0.1495 | P52: -0.0374 | Q52: 3.5 | R52: -0.55 | S52: 0.01 | T52: -2.96 | U52: =MAX(ABS(C52-L52),ABS(D52-M52),ABS(E52-N52),ABS(F52-O52),ABS(G52-P52),ABS(H52-Q52)/100,ABS(I52-R52)/100,ABS(J52-S52)/100,ABS(K52-T52)/100) | V52: =SUMPRODUCT(--(SIGN(ROUND(C52:G52,4))<>SIGN(ROUND(L52:P52,4))))+SUMPRODUCT(--(SIGN(ROUND(H52:K52,2))<>SIGN(ROUND(Q52:T52,2))))
A53: 2 | B53: SA | C53: =C8/C26-1 | D53: =D8/D26-1 | E53: =E8/E26-1 | F53: =F8/F26-1 | G53: =G8/G26-1 | H53: =(J8-J26)*100 | I53: =(K8-K26)*100 | J53: =(L8-L26)*100 | K53: =(M8-M26)*100 | L53: 0.0132 | M53: -0.0073 | N53: 0.0114 | O53: 0.003 | P53: 0.0079 | Q53: 0.3 | R53: -0.25 | S53: 0.03 | T53: -0.09 | U53: =MAX(ABS(C53-L53),ABS(D53-M53),ABS(E53-N53),ABS(F53-O53),ABS(G53-P53),ABS(H53-Q53)/100,ABS(I53-R53)/100,ABS(J53-S53)/100,ABS(K53-T53)/100) | V53: =SUMPRODUCT(--(SIGN(ROUND(C53:G53,4))<>SIGN(ROUND(L53:P53,4))))+SUMPRODUCT(--(SIGN(ROUND(H53:K53,2))<>SIGN(ROUND(Q53:T53,2))))
A54: 3 | B54: Deposits | C54: =C9/C27-1 | D54: =D9/D27-1 | E54: =E9/E27-1 | F54: =F9/F27-1 | G54: =G9/G27-1 | H54: =(J9-J27)*100 | I54: =(K9-K27)*100 | J54: =(L9-L27)*100 | K54: =(M9-M27)*100 | L54: 0.5596 | M54: 0.125 | N54: 0.1005 | O54: -0.0287 | P54: 0.2927 | Q54: 10.35 | R54: -1.28 | S54: -1.3 | T54: -7.77 | U54: =MAX(ABS(C54-L54),ABS(D54-M54),ABS(E54-N54),ABS(F54-O54),ABS(G54-P54),ABS(H54-Q54)/100,ABS(I54-R54)/100,ABS(J54-S54)/100,ABS(K54-T54)/100) | V54: =SUMPRODUCT(--(SIGN(ROUND(C54:G54,4))<>SIGN(ROUND(L54:P54,4))))+SUMPRODUCT(--(SIGN(ROUND(H54:K54,2))<>SIGN(ROUND(Q54:T54,2))))
A55: 4 | B55: ODFD | C55: =C10/C28-1 | D55: =D10/D28-1 | E55: =E10/E28-1 | F55: =F10/F28-1 | G55: =G10/G28-1 | H55: =(J10-J28)*100 | I55: =(K10-K28)*100 | J55: =(L10-L28)*100 | K55: =(M10-M28)*100 | L55: -0.3147 | M55: -0.032 | N55: -0.4418 | O55: -0.0957 | P55: -0.2521 | Q55: -4.76 | R55: 4.5 | S55: -3.05 | T55: 3.3 | U55: =MAX(ABS(C55-L55),ABS(D55-M55),ABS(E55-N55),ABS(F55-O55),ABS(G55-P55),ABS(H55-Q55)/100,ABS(I55-R55)/100,ABS(J55-S55)/100,ABS(K55-T55)/100) | V55: =SUMPRODUCT(--(SIGN(ROUND(C55:G55,4))<>SIGN(ROUND(L55:P55,4))))+SUMPRODUCT(--(SIGN(ROUND(H55:K55,2))<>SIGN(ROUND(Q55:T55,2))))
A56: 5 | B56: Grand Total | C56: =C11/C29-1 | D56: =D11/D29-1 | E56: =E11/E29-1 | F56: =F11/F29-1 | G56: =G11/G29-1 | H56: =(J11-J29)*100 | I56: =(K11-K29)*100 | J56: =(L11-L29)*100 | K56: =(M11-M29)*100 | L56: 0.3933 | M56: 0.0735 | N56: 0.0737 | O56: -0.0321 | P56: 0.211 | Q56: 7.87 | R56: -1.26 | S56: -0.98 | T56: -5.64 | U56: =MAX(ABS(C56-L56),ABS(D56-M56),ABS(E56-N56),ABS(F56-O56),ABS(G56-P56),ABS(H56-Q56)/100,ABS(I56-R56)/100,ABS(J56-S56)/100,ABS(K56-T56)/100) | V56: =SUMPRODUCT(--(SIGN(ROUND(C56:G56,4))<>SIGN(ROUND(L56:P56,4))))+SUMPRODUCT(--(SIGN(ROUND(H56:K56,2))<>SIGN(ROUND(Q56:T56,2))))
A58: CM vs LQ: computed growth and share shift vs printed (signed as printed)
A59: # | B59: Product | C59: g INSIGNIA | D59: g SIGNATURE | E59: g ASPIRE | F59: g MASS | G59: g Total | H59: Δshare INSIGNIA (pp) | I59: Δshare SIGNATURE (pp) | J59: Δshare ASPIRE (pp) | K59: Δshare MASS (pp) | L59: Printed g INSIGNIA | M59: Printed g SIGNATURE | N59: Printed g ASPIRE | O59: Printed g MASS | P59: Printed g Total | Q59: Printed Δ INSIGNIA | R59: Printed Δ SIGNATURE | S59: Printed Δ ASPIRE | T59: Printed Δ MASS | U59: Max |computed − printed| (growth; shift ÷ 100) | V59: Sign mismatches computed vs printed
A60: 1 | B60: CA | C60: =C7/C34-1 | D60: =D7/D34-1 | E60: =E7/E34-1 | F60: =F7/F34-1 | G60: =G7/G34-1 | H60: =(J7-J34)*100 | I60: =(K7-K34)*100 | J60: =(L7-L34)*100 | K60: =(M7-M34)*100 | L60: -0.0077 | M60: -0.0513 | N60: -0.085 | O60: -0.3157 | P60: -0.1072 | Q60: 6.23 | R60: 0.42 | S60: 0.2 | T60: -6.85 | U60: =MAX(ABS(C60-L60),ABS(D60-M60),ABS(E60-N60),ABS(F60-O60),ABS(G60-P60),ABS(H60-Q60)/100,ABS(I60-R60)/100,ABS(J60-S60)/100,ABS(K60-T60)/100) | V60: =SUMPRODUCT(--(SIGN(ROUND(C60:G60,4))<>SIGN(ROUND(L60:P60,4))))+SUMPRODUCT(--(SIGN(ROUND(H60:K60,2))<>SIGN(ROUND(Q60:T60,2))))
A61: 2 | B61: SA | C61: =C8/C35-1 | D61: =D8/D35-1 | E61: =E8/E35-1 | F61: =F8/F35-1 | G61: =G8/G35-1 | H61: =(J8-J35)*100 | I61: =(K8-K35)*100 | J61: =(L8-L35)*100 | K61: =(M8-M35)*100 | L61: 0.0187 | M61: 0.0022 | N61: -0.0123 | O61: 0.03 | P61: 0.0153 | Q61: 0.19 | R61: -0.21 | S61: -0.23 | T61: 0.25 | U61: =MAX(ABS(C61-L61),ABS(D61-M61),ABS(E61-N61),ABS(F61-O61),ABS(G61-P61),ABS(H61-Q61)/100,ABS(I61-R61)/100,ABS(J61-S61)/100,ABS(K61-T61)/100) | V61: =SUMPRODUCT(--(SIGN(ROUND(C61:G61,4))<>SIGN(ROUND(L61:P61,4))))+SUMPRODUCT(--(SIGN(ROUND(H61:K61,2))<>SIGN(ROUND(Q61:T61,2))))
A62: 3 | B62: Deposits | C62: =C9/C36-1 | D62: =D9/D36-1 | E62: =E9/E36-1 | F62: =F9/F36-1 | G62: =G9/G36-1 | H62: =(J9-J36)*100 | I62: =(K9-K36)*100 | J62: =(L9-L36)*100 | K62: =(M9-M36)*100 | L62: 1.0309 | M62: 0.1862 | N62: 0.1372 | O62: -0.0689 | P62: 0.4538 | Q62: 17.19 | R62: -1.94 | S62: -2.07 | T62: -13.18 | U62: =MAX(ABS(C62-L62),ABS(D62-M62),ABS(E62-N62),ABS(F62-O62),ABS(G62-P62),ABS(H62-Q62)/100,ABS(I62-R62)/100,ABS(J62-S62)/100,ABS(K62-T62)/100) | V62: =SUMPRODUCT(--(SIGN(ROUND(C62:G62,4))<>SIGN(ROUND(L62:P62,4))))+SUMPRODUCT(--(SIGN(ROUND(H62:K62,2))<>SIGN(ROUND(Q62:T62,2))))
A63: 4 | B63: ODFD | C63: =C10/C37-1 | D63: =D10/D37-1 | E63: =E10/E37-1 | F63: =F10/F37-1 | G63: =G10/G37-1 | H63: =(J10-J37)*100 | I63: =(K10-K37)*100 | J63: =(L10-L37)*100 | K63: =(M10-M37)*100 | L63: -0.3608 | M63: -0.0368 | N63: 0.0456 | O63: -0.0764 | P63: -0.2387 | Q63: -9.95 | R63: 4.15 | S63: 2.44 | T63: 3.36 | U63: =MAX(ABS(C63-L63),ABS(D63-M63),ABS(E63-N63),ABS(F63-O63),ABS(G63-P63),ABS(H63-Q63)/100,ABS(I63-R63)/100,ABS(J63-S63)/100,ABS(K63-T63)/100) | V63: =SUMPRODUCT(--(SIGN(ROUND(C63:G63,4))<>SIGN(ROUND(L63:P63,4))))+SUMPRODUCT(--(SIGN(ROUND(H63:K63,2))<>SIGN(ROUND(Q63:T63,2))))
A64: 5 | B64: Grand Total | C64: =C11/C38-1 | D64: =D11/D38-1 | E64: =E11/E38-1 | F64: =F11/F38-1 | G64: =G11/G38-1 | H64: =(J11-J38)*100 | I64: =(K11-K38)*100 | J64: =(L11-L38)*100 | K64: =(M11-M38)*100 | L64: 0.6593 | M64: 0.1171 | N64: 0.0907 | O64: -0.0752 | P64: 0.3112 | Q64: 12.62 | R64: -1.7 | S64: -1.54 | T64: -9.37 | U64: =MAX(ABS(C64-L64),ABS(D64-M64),ABS(E64-N64),ABS(F64-O64),ABS(G64-P64),ABS(H64-Q64)/100,ABS(I64-R64)/100,ABS(J64-S64)/100,ABS(K64-T64)/100) | V64: =SUMPRODUCT(--(SIGN(ROUND(C64:G64,4))<>SIGN(ROUND(L64:P64,4))))+SUMPRODUCT(--(SIGN(ROUND(H64:K64,2))<>SIGN(ROUND(Q64:T64,2))))
A67: Data points to flag before metrics (live checks)
A68: # | B68: Flag | C68: Check value (live) | D68: Unit | E68: Implication / action
A69: 1 | B69: Printed growth and share-shift tables are signed and every cell agrees in sign with the recomputed value (sign mismatches across 135 cells): | C69: =SUM(V44:V48,V52:V56,V60:V64) | D69: count | E69: Printed growth can be used directly; 10 of 16 segment × product cells declined YoY (e.g. MASS CA −49.1%, CA total −29.9%).
A70: 2 | B70: 'Growth in Allocated Segment' is the change in segment share (pp), not a growth rate — e.g. INSIGNIA Grand Total share 60.14% − 46.83% = 13.31 pp. | C70: =H48 | D70: pp | E70: Relabel as 'share shift' in any downstream metric.
A71: 3 | B71: Printed % values tie to recomputed values within rounding (max |computed − printed|); the only gaps above 0.1 pp are ODFD cells, whose balances are under ₹15 Cr: | C71: =MAX(U44:U48,U52:U56,U60:U64) | D71: % | E71: Rounding of small balances only.
A72: 4 | B72: Σ products vs printed Grand Total (max gap across all periods and segments): | C72: =MAX(ABS(C13),ABS(G13),ABS(C22),ABS(G22),ABS(C31),ABS(G31),ABS(C40),ABS(G40)) | D72: ₹ Cr | E72: Table rolls up.
A73: 5 | B73: INSIGNIA deposits more than doubled YoY (+₹27,914 Cr) while MASS deposits fell — total book growth is almost entirely INSIGNIA TD. | C73: =C9-C18 | D73: ₹ Cr | E73: Concentration in one segment / product; check if a few large depositors drive it.
A74: 6 | B74: CM MEB grand total (113,110) differs from the Balance Movement CM MAB grand total (115,449): MEB vs MAB basis. | C74: =B2_Balance_Movement!J25-G11 | D74: ₹ Cr | E74: State MEB vs MAB basis on every number.
A76: Notation and exhaustive metrics table for this block: see sheet B1_Metrics
A78: 10-question test set (3 Low / 4 Medium / 3 High) — expected answers are live formulas
A79: # | B79: Level | C79: Question | D79: Calculation | E79: Expected answer (live) | F79: Unit | G79: So what
A80: 1 | B80: Low | C80: What is INSIGNIA deposits MEB in the current month? | D80: Lookup | E80: =C9 | F80: ₹ Cr
A81: 2 | B81: Low | C81: What is the MASS share of total CM MEB? | D81: MASS GT / GT | E81: =M11 | F81: %
A82: 3 | B82: Low | C82: What was last year's grand total MEB? | D82: Lookup | E82: =G20 | F82: ₹ Cr
A83: 4 | B83: Medium | C83: What is YoY growth of the total book? | D83: CM GT / LY GT − 1 | E83: =G48 | F83: %
A84: 5 | B84: Medium | C84: How did INSIGNIA's share of the book move YoY (pp)? | D84: Share CM − share LY | E84: =H48 | F84: pp | G84: Matches printed 13.31 'Growth in Allocated Segment'.
A85: 6 | B85: Medium | C85: What is the MoM growth of CA? | D85: CM CA / LM CA − 1 | E85: =G52 | F85: %
A86: 7 | B86: Medium | C86: What share of total CM MEB is deposits (TD)? | D86: Deposits GT / GT | E86: =N9 | F86: %
A87: 8 | B87: High | C87: Recompute MASS CA YoY growth and check it against the printed −49.12%. | D87: CM MASS CA / LY MASS CA − 1 | E87: =F44 | F87: % | G87: CA in the MASS segment has halved in a year — the sharpest decline on the page.
A88: 9 | B88: High | C88: How much of the YoY grand-total growth (₹ Cr) came from INSIGNIA deposits? | D88: ΔINSIGNIA Deposits / ΔGT | E88: =(C9-C18)/(G11-G20) | F88: % | G88: More than 100% → all other cells net declined.
A89: 10 | B89: High | C89: What is YoY growth of the book excluding deposits (CASA + ODFD)? | D89: (GT − Dep) CM / (GT − Dep) LY − 1 | E89: =(G11-G9)/(G20-G18)-1 | F89: % | G89: CASA is shrinking while TD doubles → cost of funds rising.
A91: What this page cannot support (feeds the data request)
A92: Not derivable: cost of funds / interest rates by segment, customer counts and average balance per customer, number of large depositors behind the INSIGNIA TD jump, maturity profile of the TD book, intra-month volatility (MEB only here), RM / branch split, and the definition and direction of the '3 Cr' filters.
A94: ⚠ DRAFT ONLY — Requires review and approval by a qualified Alvarez and Marsal professional before use.

Sheet B1_Metrics
A1: Block 1 — MEB by product × segment: notation and metrics
A2: Format: Notation → Exhaustive metrics table | Example column = live Excel formula on the block sheet (green = cross-sheet)
A3: ⚠ DRAFT ONLY — Requires review and approval by a qualified Alvarez and Marsal professional before use.
A5: Notation
B6: Symbol | C6: Meaning
B7: MEB | C7: Month-end balance, ₹ Cr
B8: B(p, s, t) | C8: MEB of product p (CA, SA, Deposits, ODFD) in segment s (INSIGNIA, SIGNATURE, ASPIRE, MASS) at period t
B9: t | C9: CM = current month; LM = last month; LQ = last quarter-end month; LY = same month last year
B10: T(p,t) / T(s,t) | C10: Product total across segments / segment total across products
B11: GT(t) | C11: Grand Total MEB
B12: sh(s|p,t) | C12: Segment share within product = B(p,s,t) ÷ T(p,t)
B13: g(x) | C13: Growth = x(CM) ÷ x(t) − 1
B14: Δsh | C14: Share shift in pp = (sh(CM) − sh(t)) × 100 — this is what the page calls 'Growth in Allocated Segment'
B15: CASA | C15: CA + SA
B16: ± | C16: Printed values are signed; computed values are compared sign-for-sign
B17: Values are ₹ Cr month-end balances; growth in %, share shifts in pp; all periods actual.
A19: Exhaustive metrics table
A20: # | B20: Metric family | C20: Pipeline-ready metric | D20: Definition / formula | E20: Applies to | F20: Example | G20: Executable Formula | H20: Output Type
A21: 1 | B21: Fact lookup | C21: Product × segment MEB | D21: B(p,s,t) | E21: 4 products × 4 segments × 4 periods (64 cells) | F21: Deposits INSIGNIA CM / LM / LQ / LY 52,910.64 / 33,926.56 / 26,052.53 / 24,996.33 | G21: B(p,s,t)
A22: 2 | B22: Fact lookup | C22: Product totals | D22: T(p,t) as printed | E22: 4 × 4 | F22: CM: CA 6,197.51; SA 19,422.88; Deposits 87,472.57; ODFD 16.84 | G22: B(Total,CM MEB)
A23: 3 | B23: Fact lookup | C23: Segment totals | D23: T(s,t) as printed | E23: 4 × 4 | F23: CM: 68,026.83 / 11,081.29 / 8,628.16 / 25,373.53 | G23: B(Grand Total,CM MEB / INSIGNIA)
A24: 4 | B24: Fact lookup | C24: Grand Total | D24: GT(t) | E24: 4 periods | F24: CM / LM / LQ / LY 113,109.81 / 93,398.40 / 86,263.02 / 87,794.42 | G24: B(Grand Total,CM MEB / Total)
A25: 5 | B25: Roll-up check | C25: Products to Grand Total | D25: GT(t) − Σp T(p,t) | E25: 4 periods × 5 columns | F25: CM -0.01 / 0.00 / 0.01 / 0.00 / 0.01 | G25: B(Grand Total,CM MEB / Total)-B(Grand Total,CM MEB / Total) | H25: Cr
A26: 6 | B26: Roll-up check | C26: Segments to product total | D26: T(p,t) − Σs B(p,s,t) | E26: 20 rows | F26: CM 0.00 / 0.00 / 0.00 / -0.01 / 0.00 | G26: B(Deposits,Total,CM MEB)-B(Deposits,Total,CM MEB) | H26: Cr
A27: 7 | B27: Mix & share | C27: Segment share within product | D27: sh(s|p,CM) | E27: 4 products + GT × 4 segments × 4 periods | F27: Deposits CM 60.5% / 8.6% / 7.4% / 23.5%; LY 42.1% / 10.1% / 9.3% / 38.4% | G27: Deposits(INSIGNIA,CM) | H27: %
A28: 8 | B28: Mix & share | C28: Segment share of Grand Total | D28: T(s,CM) ÷ GT(CM) | E28: 4 segments × 4 periods | F28: CM 60.1% / 9.8% / 7.6% / 22.4%; LY 46.8% / 11.0% / 8.8% / 33.3% | G28: GT(INSIGNIA,CM) | H28: %
A29: 9 | B29: Mix & share | C29: Product share of Grand Total | D29: T(p,t) ÷ GT(t) | E29: 4 products × 4 periods | F29: CM 5.5% / 17.2% / 77.3% / 0.0% (CA / SA / Dep / ODFD) | G29: B(CA,CM MEB / Total)/B(Grand Total,CM MEB / Total) | H29: %
A30: 10 | B30: Mix & share | C30: CASA share of book | D30: (T(CA) + T(SA)) ÷ GT | E30: 4 periods | F30: CM 22.7%; LM 27.5%; LY 32.4% | G30: (B(CA,CM MEB / Total)+B(SA,CM MEB / Total))/B(Grand Total,CM MEB / Total) | H30: %
A31: 11 | B31: Mix & share | C31: Share shift ('Growth in Allocated Segment') | D31: Δsh = (sh(CM) − sh(t)) × 100 | E31: 5 rows × 4 segments × 3 comparisons | F31: vs LY, GT row: +13.3 pp / -1.2 pp / -1.2 pp / -10.9 pp; vs LM +7.9 pp / -1.3 pp / -1.0 pp / -5.6 pp | G31: Growth(Grand Total,Selected Segment / CM Vs LY,INSIGNIA) | H31: %
A32: 12 | B32: Growth & momentum | C32: YoY growth by segment × product | D32: g = B(CM) ÷ B(LY) − 1 | E32: 5 × 5 cells | F32: CA -21.5% / -20.5% / -20.2% / -49.1% / -29.9%; Deposits +111.7% / +24.9% / +17.5% / -9.8% / +47.4% | G32: B(CA,INSIGNIA,CM MEB)/B(CA,INSIGNIA,LY MEB)-1 | H32: %
A33: 13 | B33: Growth & momentum | C33: YoY growth — totals | D33: g(T(s)) and g(GT) | E33: 4 segments + GT | F33: +65.5% / +14.4% / +11.3% / -13.2% / +28.8% | G33: B(Grand Total,CM MEB / INSIGNIA)/B(Grand Total,LY MEB / INSIGNIA)-1 | H33: %
A34: 14 | B34: Growth & momentum | C34: MoM growth | D34: g = B(CM) ÷ B(LM) − 1 | E34: 5 × 5 | F34: GT row +39.3% / +7.4% / +7.4% / -3.2% / +21.1%; Deposits +56.0% / +12.5% / +10.0% / -2.9% / +29.3% | G34: B(Grand Total,CM MEB / INSIGNIA)/B(Grand Total,LM MEB / INSIGNIA)-1 | H34: %
A35: 15 | B35: Growth & momentum | C35: QoQ growth | D35: g = B(CM) ÷ B(LQ) − 1 | E35: 5 × 5 | F35: GT row +65.9% / +11.7% / +9.1% / -7.5% / +31.1%; CA -0.8% / -5.1% / -8.5% / -31.6% / -10.7% | G35: B(CM MEB)/B(LQ MEB)-1 | H35: %
A36: 16 | B36: Growth & momentum | C36: YoY growth ex deposits (CASA + ODFD) | D36: (GT − T(Dep))(CM) ÷ (GT − T(Dep))(LY) − 1 | E36: Window | F36: -9.9% | G36: (B(Grand Total,CM MEB / Total)-B(Deposits,CM MEB / Total))/(B(Grand Total,LY MEB / Total)-B(Deposits,LY MEB / Total))-1 | H36: %
... A48: 28 | B48: Data integrity | C48: MEB vs MAB basis | D48: GT(CM) MEB vs CM* MAB (Block 2) | E48: Page | F48: MEB 113,109.81 vs MAB 115,448.64 | G48: B(Grand Total,CM MEB / Total) | H48: Cr
A50: ⚠ DRAFT ONLY — Requires review and approval by a qualified Alvarez and Marsal professional before use.

Sheet B2_Balance_Movement
A1: Block 2 — Balance Movement (MAB) by segment × product
A2: Source: Book Growth Analysis.pdf, 'Balance Movement' (R/Z/C/B MEB/MAB toggle = MAB) | ₹ Cr
A3: ⚠ DRAFT ONLY — Requires review and approval by a qualified Alvarez and Marsal professional before use.
A5: A. Source data (blue) with line-level live calculations
A6: # | B6: Segment | C6: Product | D6: CD* | E6: CD < 3 Cr* | F6: CD < 3 Ind Cr* | G6: PD* | H6: PD < 3 Cr* | I6: PD < 3 Ind Cr* | J6: CM* | K6: CM < 3 Cr* | L6: CM < 3 Ind Cr* | M6: LM* | N6: LM < 3 Cr* | O6: LM < 3 Ind Cr* | P6: LY* | Q6: LY < 3 Cr* | R6: LY < 3 Ind Cr* | S6: LYCM* | T6: LYCM < 3 Cr* | U6: LYCM < 3 Ind Cr* | V6: < 3 Cr share of CM | W6: < 3 Ind Cr share of CM | X6: CM vs LM growth | Y6: CM vs LY growth | Z6: CM vs LYCM growth | AA6: CD − PD (daily Δ) | AB6: CM MAB ÷ CM MEB (Block 1) | AC6: Share of CM grand total
A7: 1 | B7: INSIGNIA | C7: CA | D7: 3632 | E7: 1993 | F7: 165 | G7: 3623 | H7: 1992 | I7: 164 | J7: 3632.2 | K7: 1993.14 | L7: 164.65 | M7: 3654.79 | N7: 2007 | O7: 166.48 | P7: 3771.85 | Q7: 2005.68 | R7: 168.68 | S7: 3520.74 | T7: 1820.98 | U7: 152.38 | V7: =K7/J7 | W7: =L7/J7 | X7: =J7/M7-1 | Y7: =J7/P7-1 | Z7: =J7/S7-1 | AA7: =D7-G7 | AB7: =J7/B1_MEB_Periods!C7 | AC7: =J7/$J$27
A8: 2 | B8: INSIGNIA | C8: SA | D8: 11292 | E8: 8238 | F8: 7636 | G8: 11277 | H8: 8224 | I8: 7623 | J8: 11292.23 | K8: 8237.78 | L8: 7636.22 | M8: 11009.63 | N8: 8255.49 | O8: 7660.36 | P8: 10755.15 | Q8: 8328.96 | R8: 7737.18 | S8: 10769.1 | T8: 8986.49 | U8: 8276.84 | V8: =K8/J8 | W8: =L8/J8 | X8: =J8/M8-1 | Y8: =J8/P8-1 | Z8: =J8/S8-1 | AA8: =D8-G8 | AB8: =J8/B1_MEB_Periods!C8 | AC8: =J8/$J$27
A9: 3 | B9: INSIGNIA | C9: Deposits | D9: 53834 | E9: 25134 | F9: 17074 | G9: 53779 | H9: 25067 | I9: 17004 | J9: 53834.13 | K9: 25133.69 | L9: 17073.96 | M9: 34820.85 | N9: 24584.69 | O9: 16922.51 | P9: 24851.69 | Q9: 22642.5 | R9: 15771.57 | S9: 21769.31 | T9: 20035.28 | U9: 14567.77 | V9: =K9/J9 | W9: =L9/J9 | X9: =J9/M9-1 | Y9: =J9/P9-1 | Z9: =J9/S9-1 | AA9: =D9-G9 | AB9: =J9/B1_MEB_Periods!C9 | AC9: =J9/$J$27
A10: 4 | B10: INSIGNIA | C10: ODFD | D10: 11 | E10: 11 | F10: 4 | G10: 12 | H10: 12 | I10: 4 | J10: 10.93 | K10: 10.93 | L10: 3.63 | M10: 12.92 | N10: 9.84 | O10: 3.22 | P10: 14.31 | Q10: 14.31 | R10: 2.71 | S10: 5.1 | T10: 5.1 | U10: 3.59 | V10: =K10/J10 | W10: =L10/J10 | X10: =J10/M10-1 | Y10: =J10/P10-1 | Z10: =J10/S10-1 | AA10: =D10-G10 | AB10: =J10/B1_MEB_Periods!C10 | AC10: =J10/$J$27
A11: 5 | B11: SIGNATURE | C11: CA | D11: 464 | E11: 405 | F11: 22 | G11: 465 | H11: 405 | I11: 22 | J11: 464.43 | K11: 404.88 | L11: 22.31 | M11: 448.61 | N11: 407.99 | O11: 23.14 | P11: 451.09 | Q11: 414.86 | R11: 21.05 | S11: 403.49 | T11: 377.86 | U11: 19.1 | V11: =K11/J11 | W11: =L11/J11 | X11: =J11/M11-1 | Y11: =J11/P11-1 | Z11: =J11/S11-1 | AA11: =D11-G11 | AB11: =J11/B1_MEB_Periods!D7 | AC11: =J11/$J$27
A12: 6 | B12: SIGNATURE | C12: SA | D12: 3163 | E12: 2821 | F12: 2634 | G12: 3158 | H12: 2816 | I12: 2630 | J12: 3162.61 | K12: 2820.83 | L12: 2634.12 | M12: 3131.39 | N12: 2840.13 | O12: 2648.78 | P12: 2975.19 | Q12: 2750.52 | R12: 2555.06 | S12: 2889.62 | T12: 2766.81 | U12: 2554.14 | V12: =K12/J12 | W12: =L12/J12 | X12: =J12/M12-1 | Y12: =J12/P12-1 | Z12: =J12/S12-1 | AA12: =D12-G12 | AB12: =J12/B1_MEB_Periods!D8 | AC12: =J12/$J$27
A13: 7 | B13: SIGNATURE | C13: Deposits | D13: 7691 | E13: 6488 | F13: 5165 | G13: 7685 | H13: 6479 | I13: 5156 | J13: 7691.48 | K13: 6488.34 | L13: 5164.5 | M13: 6971.53 | N13: 6415.62 | O13: 5117.17 | P13: 5987.47 | Q13: 5815.5 | R13: 4671.18 | S13: 5563.27 | T13: 5436.99 | U13: 4478.53 | V13: =K13/J13 | W13: =L13/J13 | X13: =J13/M13-1 | Y13: =J13/P13-1 | Z13: =J13/S13-1 | AA13: =D13-G13 | AB13: =J13/B1_MEB_Periods!D9 | AC13: =J13/$J$27
A14: 8 | B14: SIGNATURE | C14: ODFD | D14: 3 | E14: 3 | F14: 1 | G14: 3 | H14: 3 | I14: 1 | J14: 3.39 | K14: 3.39 | L14: 1.34 | M14: 3.54 | N14: 3.54 | O14: 1.42 | P14: 4.75 | Q14: 4.75 | R14: 2.01 | S14: 1.8 | T14: 1.8 | U14: 1.57 | V14: =K14/J14 | W14: =L14/J14 | X14: =J14/M14-1 | Y14: =J14/P14-1 | Z14: =J14/S14-1 | AA14: =D14-G14 | AB14: =J14/B1_MEB_Periods!D10 | AC14: =J14/$J$27
A15: 9 | B15: ASPIRE | C15: CA | D15: 512 | E15: 487 | F15: 25 | G15: 512 | H15: 483 | I15: 25 | J15: 512.41 | K15: 486.51 | L15: 24.9 | M15: 519.02 | N15: 492.3 | O15: 25.79 | P15: 519.49 | Q15: 501.14 | R15: 22.5 | S15: 492.75 | T15: 452.15 | U15: 25.58 | V15: =K15/J15 | W15: =L15/J15 | X15: =J15/M15-1 | Y15: =J15/P15-1 | Z15: =J15/S15-1 | AA15: =D15-G15 | AB15: =J15/B1_MEB_Periods!E7 | AC15: =J15/$J$27
A16: 10 | B16: ASPIRE | C16: SA | D16: 1601 | E16: 1459 | F16: 1358 | G16: 1597 | H16: 1458 | I16: 1357 | J16: 1600.8 | K16: 1459.24 | L16: 1357.7 | M16: 1571.98 | N16: 1438.74 | O16: 1340.47 | P16: 1489.31 | Q16: 1406.7 | R16: 1308.01 | S16: 1397.93 | T16: 1331.13 | U16: 1238.57 | V16: =K16/J16 | W16: =L16/J16 | X16: =J16/M16-1 | Y16: =J16/P16-1 | Z16: =J16/S16-1 | AA16: =D16-G16 | AB16: =J16/B1_MEB_Periods!E8 | AC16: =J16/$J$27
A17: 11 | B17: ASPIRE | C17: Deposits | D17: 6650 | E17: 5238 | F17: 4198 | G17: 6644 | H17: 5232 | I17: 4193 | J17: 6649.5 | K17: 5238.19 | L17: 4198.4 | M17: 6048.97 | N17: 5222.25 | O17: 4195.7 | P17: 5465.44 | Q17: 4833.6 | R17: 3976.14 | S17: 4964.08 | T17: 4556.55 | U17: 3827.28 | V17: =K17/J17 | W17: =L17/J17 | X17: =J17/M17-1 | Y17: =J17/P17-1 | Z17: =J17/S17-1 | AA17: =D17-G17 | AB17: =J17/B1_MEB_Periods!E9 | AC17: =J17/$J$27
A18: 12 | B18: ASPIRE | C18: ODFD | D18: 2 | E18: 2 | F18: 1 | G18: 2 | H18: 2 | I18: 1 | J18: 1.57 | K18: 1.57 | L18: 0.85 | M18: 2.12 | N18: 2.12 | O18: 0.8 | P18: 2.07 | Q18: 2.07 | R18: 1.29 | S18: 0.96 | T18: 0.96 | U18: 0.67 | V18: =K18/J18 | W18: =L18/J18 | X18: =J18/M18-1 | Y18: =J18/P18-1 | Z18: =J18/S18-1 | AA18: =D18-G18 | AB18: =J18/B1_MEB_Periods!E10 | AC18: =J18/$J$27
A19: 13 | B19: MASS | C19: CA | D19: 1430 | E19: 949 | F19: 38 | G19: 1429 | H19: 946 | I19: 38 | J19: 1429.87 | K19: 949.08 | L19: 37.56 | M19: 1488.67 | N19: 928.15 | O19: 36.43 | P19: 1517.97 | Q19: 912.73 | R19: 30.39 | S19: 1018.29 | T19: 754.52 | U19: 28.11 | V19: =K19/J19 | W19: =L19/J19 | X19: =J19/M19-1 | Y19: =J19/P19-1 | Z19: =J19/S19-1 | AA19: =D19-G19 | AB19: =J19/B1_MEB_Periods!F7 | AC19: =J19/$J$27
A20: 14 | B20: MASS | C20: SA | D20: 3425 | E20: 2873 | F20: 2673 | G20: 3420 | H20: 2869 | I20: 2669 | J20: 3424.93 | K20: 2873.5 | L20: 2672.71 | M20: 3310.68 | N20: 2779.41 | O20: 2576.04 | P20: 3585.5 | Q20: 2632.36 | R20: 2430.85 | S20: 2760.59 | T20: 2248.48 | U20: 2070.45 | V20: =K20/J20 | W20: =L20/J20 | X20: =J20/M20-1 | Y20: =J20/P20-1 | Z20: =J20/S20-1 | AA20: =D20-G20 | AB20: =J20/B1_MEB_Periods!F8 | AC20: =J20/$J$27
A21: 15 | B21: MASS | C21: Deposits | D21: 21726 | E21: 7994 | F21: 3431 | G21: 21745 | H21: 7983 | I21: 3422 | J21: 21726.17 | K21: 7994.29 | L21: 3430.71 | M21: 21873.22 | N21: 7730.07 | O21: 3287.99 | P21: 21698.96 | Q21: 6791.36 | R21: 2802.95 | S21: 17832.35 | T21: 5330.82 | U21: 2456.2 | V21: =K21/J21 | W21: =L21/J21 | X21: =J21/M21-1 | Y21: =J21/P21-1 | Z21: =J21/S21-1 | AA21: =D21-G21 | AB21: =J21/B1_MEB_Periods!F9 | AC21: =J21/$J$27
A22: 16 | B22: MASS | C22: ODFD | D22: 12 | E22: 8 | F22: 3 | G22: 12 | H22: 8 | I22: 3 | J22: 11.98 | K22: 8.27 | L22: 2.91 | M22: 12.86 | N22: 3.93 | O22: 2.95 | P22: 8.7 | Q22: 8.7 | R22: 3.07 | S22: 7 | T22: 7 | U22: 2.99 | V22: =K22/J22 | W22: =L22/J22 | X22: =J22/M22-1 | Y22: =J22/P22-1 | Z22: =J22/S22-1 | AA22: =D22-G22 | AB22: =J22/B1_MEB_Periods!F10 | AC22: =J22/$J$27
B24: Σ all lines (computed) | D24: =SUM(D7:D22) | E24: =SUM(E7:E22) | F24: =SUM(F7:F22) | G24: =SUM(G7:G22) | H24: =SUM(H7:H22) | I24: =SUM(I7:I22) | J24: =SUM(J7:J22) | K24: =SUM(K7:K22) | ... U24: =SUM(U7:U22)
B25: Grand Total (printed) | D25: 115449 | E25: 64104 | F25: 44426 | G25: 115364 | H25: 63980 | I25: 44312 | J25: 115448.64 | K25: 64103.64 | L25: 44426.48 | M25: 94880.79 | N25: 63121.29 | O25: 44009.26 | P25: 83098.91 | Q25: 59065.73 | R25: 41504.63 | S25: 73396.38 | T25: 54112.92 | U25: 39703.76 | V25: =K25/J25 | W25: =L25/J25 | X25: =J25/M25-1 | Y25: =J25/P25-1 | Z25: =J25/S25-1 | AA25: =D25-G25
B26: Gap printed − computed | D26: =D25-D24 | E26: =E25-E24 | F26: =F25-F24 | G26: =G25-G24 | H26: =H25-H24 | I26: =I25-I24 | J26: =J25-J24 | K26: =K25-K24 | ... U26: =U25-U24
B27: Grand Total used for shares | D27: =D25 | E27: =E25 | F27: =F25 | G27: =G25 | H27: =H25 | I27: =I25 | J27: =J25 | K27: =K25 | ... U27: =U25
A29: B. Roll-ups by segment and by product (SUMIFS)
A30: # | B30: Level | C30: Item | D30: CD* | E30: CD < 3 Cr* | F30: CD < 3 Ind Cr* | G30: PD* | H30: PD < 3 Cr* | I30: PD < 3 Ind Cr* | J30: CM* | K30: CM < 3 Cr* | L30: CM < 3 Ind Cr* | M30: LM* | N30: LM < 3 Cr* | O30: LM < 3 Ind Cr* | P30: LY* | Q30: LY < 3 Cr* | R30: LY < 3 Ind Cr* | S30: LYCM* | T30: LYCM < 3 Cr* | U30: LYCM < 3 Ind Cr* | V30: < 3 Cr share of CM | W30: < 3 Ind Cr share of CM | X30: CM vs LM growth | Y30: CM vs LY growth | Z30: CM vs LYCM growth | AA30: CD − PD | AC30: Share of CM grand total
A31: 1 | B31: Segment | C31: INSIGNIA | D31: =SUMIFS(D$7:D$22,$B$7:$B$22,$C31) | E31: =SUMIFS(E$7:E$22,$B$7:$B$22,$C31) | F31: =SUMIFS(F$7:F$22,$B$7:$B$22,$C31) | G31: =SUMIFS(G$7:G$22,$B$7:$B$22,$C31) | H31: =SUMIFS(H$7:H$22,$B$7:$B$22,$C31) | I31: =SUMIFS(I$7:I$22,$B$7:$B$22,$C31) | J31: =SUMIFS(J$7:J$22,$B$7:$B$22,$C31) | K31: =SUMIFS(K$7:K$22,$B$7:$B$22,$C31) | ... U31: =SUMIFS(U$7:U$22,$B$7:$B$22,$C31) | V31: =K31/J31 | W31: =L31/J31 | X31: =J31/M31-1 | Y31: =J31/P31-1 | Z31: =J31/S31-1 | AA31: =D31-G31 | AC31: =J31/$J$27
A32: 2 | B32: Segment | C32: SIGNATURE | D32: =SUMIFS(D$7:D$22,$B$7:$B$22,$C32) | E32: =SUMIFS(E$7:E$22,$B$7:$B$22,$C32) | F32: =SUMIFS(F$7:F$22,$B$7:$B$22,$C32) | G32: =SUMIFS(G$7:G$22,$B$7:$B$22,$C32) | H32: =SUMIFS(H$7:H$22,$B$7:$B$22,$C32) | I32: =SUMIFS(I$7:I$22,$B$7:$B$22,$C32) | J32: =SUMIFS(J$7:J$22,$B$7:$B$22,$C32) | K32: =SUMIFS(K$7:K$22,$B$7:$B$22,$C32) | ... U32: =SUMIFS(U$7:U$22,$B$7:$B$22,$C32) | V32: =K32/J32 | W32: =L32/J32 | X32: =J32/M32-1 | Y32: =J32/P32-1 | Z32: =J32/S32-1 | AA32: =D32-G32 | AC32: =J32/$J$27
A33: 3 | B33: Segment | C33: ASPIRE | D33: =SUMIFS(D$7:D$22,$B$7:$B$22,$C33) | E33: =SUMIFS(E$7:E$22,$B$7:$B$22,$C33) | F33: =SUMIFS(F$7:F$22,$B$7:$B$22,$C33) | G33: =SUMIFS(G$7:G$22,$B$7:$B$22,$C33) | H33: =SUMIFS(H$7:H$22,$B$7:$B$22,$C33) | I33: =SUMIFS(I$7:I$22,$B$7:$B$22,$C33) | J33: =SUMIFS(J$7:J$22,$B$7:$B$22,$C33) | K33: =SUMIFS(K$7:K$22,$B$7:$B$22,$C33) | ... U33: =SUMIFS(U$7:U$22,$B$7:$B$22,$C33) | V33: =K33/J33 | W33: =L33/J33 | X33: =J33/M33-1 | Y33: =J33/P33-1 | Z33: =J33/S33-1 | AA33: =D33-G33 | AC33: =J33/$J$27
A34: 4 | B34: Segment | C34: MASS | D34: =SUMIFS(D$7:D$22,$B$7:$B$22,$C34) | E34: =SUMIFS(E$7:E$22,$B$7:$B$22,$C34) | F34: =SUMIFS(F$7:F$22,$B$7:$B$22,$C34) | G34: =SUMIFS(G$7:G$22,$B$7:$B$22,$C34) | H34: =SUMIFS(H$7:H$22,$B$7:$B$22,$C34) | I34: =SUMIFS(I$7:I$22,$B$7:$B$22,$C34) | J34: =SUMIFS(J$7:J$22,$B$7:$B$22,$C34) | K34: =SUMIFS(K$7:K$22,$B$7:$B$22,$C34) | ... U34: =SUMIFS(U$7:U$22,$B$7:$B$22,$C34) | V34: =K34/J34 | W34: =L34/J34 | X34: =J34/M34-1 | Y34: =J34/P34-1 | Z34: =J34/S34-1 | AA34: =D34-G34 | AC34: =J34/$J$27
A35: 5 | B35: Product | C35: CA | D35: =SUMIFS(D$7:D$22,$C$7:$C$22,$C35) | E35: =SUMIFS(E$7:E$22,$C$7:$C$22,$C35) | F35: =SUMIFS(F$7:F$22,$C$7:$C$22,$C35) | G35: =SUMIFS(G$7:G$22,$C$7:$C$22,$C35) | H35: =SUMIFS(H$7:H$22,$C$7:$C$22,$C35) | I35: =SUMIFS(I$7:I$22,$C$7:$C$22,$C35) | J35: =SUMIFS(J$7:J$22,$C$7:$C$22,$C35) | K35: =SUMIFS(K$7:K$22,$C$7:$C$22,$C35) | ... U35: =SUMIFS(U$7:U$22,$C$7:$C$22,$C35) | V35: =K35/J35 | W35: =L35/J35 | X35: =J35/M35-1 | Y35: =J35/P35-1 | Z35: =J35/S35-1 | AA35: =D35-G35 | AC35: =J35/$J$27
A36: 6 | B36: Product | C36: SA | D36: =SUMIFS(D$7:D$22,$C$7:$C$22,$C36) | E36: =SUMIFS(E$7:E$22,$C$7:$C$22,$C36) | F36: =SUMIFS(F$7:F$22,$C$7:$C$22,$C36) | G36: =SUMIFS(G$7:G$22,$C$7:$C$22,$C36) | H36: =SUMIFS(H$7:H$22,$C$7:$C$22,$C36) | I36: =SUMIFS(I$7:I$22,$C$7:$C$22,$C36) | J36: =SUMIFS(J$7:J$22,$C$7:$C$22,$C36) | K36: =SUMIFS(K$7:K$22,$C$7:$C$22,$C36) | ... U36: =SUMIFS(U$7:U$22,$C$7:$C$22,$C36) | V36: =K36/J36 | W36: =L36/J36 | X36: =J36/M36-1 | Y36: =J36/P36-1 | Z36: =J36/S36-1 | AA36: =D36-G36 | AC36: =J36/$J$27
A37: 7 | B37: Product | C37: Deposits | D37: =SUMIFS(D$7:D$22,$C$7:$C$22,$C37) | E37: =SUMIFS(E$7:E$22,$C$7:$C$22,$C37) | F37: =SUMIFS(F$7:F$22,$C$7:$C$22,$C37) | G37: =SUMIFS(G$7:G$22,$C$7:$C$22,$C37) | H37: =SUMIFS(H$7:H$22,$C$7:$C$22,$C37) | I37: =SUMIFS(I$7:I$22,$C$7:$C$22,$C37) | J37: =SUMIFS(J$7:J$22,$C$7:$C$22,$C37) | K37: =SUMIFS(K$7:K$22,$C$7:$C$22,$C37) | ... U37: =SUMIFS(U$7:U$22,$C$7:$C$22,$C37) | V37: =K37/J37 | W37: =L37/J37 | X37: =J37/M37-1 | Y37: =J37/P37-1 | Z37: =J37/S37-1 | AA37: =D37-G37 | AC37: =J37/$J$27
A38: 8 | B38: Product | C38: ODFD | D38: =SUMIFS(D$7:D$22,$C$7:$C$22,$C38) | E38: =SUMIFS(E$7:E$22,$C$7:$C$22,$C38) | F38: =SUMIFS(F$7:F$22,$C$7:$C$22,$C38) | G38: =SUMIFS(G$7:G$22,$C$7:$C$22,$C38) | H38: =SUMIFS(H$7:H$22,$C$7:$C$22,$C38) | I38: =SUMIFS(I$7:I$22,$C$7:$C$22,$C38) | J38: =SUMIFS(J$7:J$22,$C$7:$C$22,$C38) | K38: =SUMIFS(K$7:K$22,$C$7:$C$22,$C38) | ... U38: =SUMIFS(U$7:U$22,$C$7:$C$22,$C38) | V38: =K38/J38 | W38: =L38/J38 | X38: =J38/M38-1 | Y38: =J38/P38-1 | Z38: =J38/S38-1 | AA38: =D38-G38 | AC38: =J38/$J$27
A41: Data points to flag before metrics (live checks)
A42: # | B42: Flag | C42: Check value (live) | D42: Unit | E42: Implication / action
A43: 1 | B43: Printed Grand Total vs Σ lines — max absolute gap across the 18 columns: | C43: =MAX(ABS(MIN(D26:U26)),MAX(D26:U26)) | D43: ₹ Cr | E43: Rounding (CD/PD columns are printed to whole ₹ Cr).
A44: 2 | B44: CM* grand total equals the MAB page grand total (115,448.64) and CM vs LM / CM vs LY diffs there equal CM − LM* and CM − LY* here. | C44: =J25-M25 | D44: ₹ Cr | E44: Confirms LM* / LY* are the comparison bases used on the MAB page.
A45: 3 | B45: Customers below ₹3 Cr hold only about half of CM MAB; < 3 Cr share of CM MAB: | C45: =V25 | D45: % | E45: The ≥ ₹3 Cr book (large / institutional) drives growth.
A46: 4 | B46: CD* and CM* are near-identical (the CD view is the current month to date): CD − CM grand total | C46: =D25-J25 | D46: ₹ Cr | E46: Use CM* as the month figure.
A47: 5 | B47: Daily movement CD − PD at grand total: | C47: =D25-G25 | D47: ₹ Cr | E47: Small; MASS deposits moved opposite to INSIGNIA.
A49: Notation and exhaustive metrics table for this block: see sheet B2_Metrics
A52: ⚠ DRAFT ONLY — Requires review and approval by a qualified Alvarez and Marsal professional before use.

Sheet B2_Metrics
A1: Block 2 — Balance Movement (MAB): notation and metrics
A2: Format: Notation → Exhaustive metrics table | Example column = live Excel formula on the block sheet (green = cross-sheet)
A3: ⚠ DRAFT ONLY — Requires review and approval by a qualified Alvarez and Marsal professional before use.
A5: Notation
B6: Symbol | C6: Meaning
B7: MAB | C7: Monthly average balance, ₹ Cr
B8: M(s,p,v) | C8: MAB of segment s, product p for view v
B9: v | C9: CD = current day (MTD); PD = previous day; CM = current month; LM = last month; LY = last year; LYCM = last-year current-month basis
B10: v < 3 Cr / v < 3 Ind Cr | C10: Sub-book of view v for customers below ₹3 Cr, and for individual customers below ₹3 Cr
B11: GT(v) | C11: Grand Total MAB for view v
B12: g(v) | C12: M(CM) ÷ M(v) − 1
B13: sh3 / shI | C13: < 3 Cr share = v < 3 Cr ÷ v; individual share = v < 3 Ind Cr ÷ v
B14: MAB/MEB | C14: CM MAB ÷ CM MEB from Block 1
B15: Values are ₹ Cr monthly average balances; growth in %, shares in %.
A17: Exhaustive metrics table
A18: # | B18: Metric family | C18: Pipeline-ready metric | D18: Definition / formula | E18: Applies to | F18: Example | G18: Executable Formula | H18: Output Type
A19: 1 | B19: Fact lookup | C19: Segment × product MAB | D19: M(s,p,v) | E19: 16 lines × 18 views (288 cells) | F19: INSIGNIA Deposits CM / LM / LY / LYCM 53,834.13 / 34,820.85 / 24,851.69 / 21,769.31 | G19: M(s,p,v)
A20: 2 | B20: Fact lookup | C20: Grand Total MAB | D20: GT(v) | E20: 18 views | F20: CD / CM / LM / LY / LYCM 115,449.00 / 115,448.64 / 94,880.79 / 83,098.91 / 73,396.38 | G20: M(Grand Total,v)
A21: 3 | B21: Roll-up check | C21: Lines to Grand Total | D21: GT(v) − Σ M(s,p,v) | E21: 18 views | F21: CD line roll-up gap: 1.00 | G21: M(CD* / Grand Total)-(M(CD* / INSIGNIA / - / CA)+M(CD* / INSIGNIA / - / SA)+M(CD* / INSIGNIA / - / Deposits)+M(CD* / INSIGNIA / - / ODFD)+M(CD* / SIGNATURE / - / CA)+M(CD* / SIGNATURE / - / SA)+M(CD* / SIGNATURE / - / Deposits)+M(CD* / SIGNATURE / - / ODFD)+M(CD* / ASPIRE / - / CA)+M(CD* / ASPIRE / - / SA)+M(CD* / ASPIRE / - / Deposits)+M(CD* / ASPIRE / - / ODFD)+M(CD* / MASS / - / CA)+M(CD* / MASS / - / SA)+M(CD* / MASS / - / Deposits)+M(CD* / MASS / - / ODFD)) | H21: Cr
A22: 4 | B22: Volume aggregates | C22: Segment MAB | D22: Σp M(s,p,CM) | E22: 4 segments × 18 views | F22: CM 68,769.49 / 11,321.91 / 8,764.28 / 26,592.95 | G22: M(CM* / INSIGNIA / - / CA)+M(CM* / INSIGNIA / - / SA)+M(CM* / INSIGNIA / - / Deposits)+M(CM* / INSIGNIA / - / ODFD) | H22: Cr
A23: 5 | B23: Volume aggregates | C23: Product MAB | D23: Σs M(s,p,CM) | E23: 4 products × 18 views | F23: CM 6,038.91 / 19,480.57 / 89,901.28 / 27.87 | G23: M(CM* / INSIGNIA / - / CA)+M(CM* / SIGNATURE / - / CA)+M(CM* / ASPIRE / - / CA)+M(CM* / MASS / - / CA) | H23: Cr
A24: 6 | B24: Volume aggregates | C24: CASA MAB | D24: M(CA) + M(SA) | E24: 18 views | F24: CM 25,519.48; LY 25,065.55 | G24: (M(CM* / INSIGNIA / - / CA)+M(CM* / SIGNATURE / - / CA)+M(CM* / ASPIRE / - / CA)+M(CM* / MASS / - / CA))+(M(CM* / INSIGNIA / - / SA)+M(CM* / SIGNATURE / - / SA)+M(CM* / ASPIRE / - / SA)+M(CM* / MASS / - / SA)) | H24: Cr
A25: 7 | B25: Mix & share | C25: Segment share of GT | D25: Σp M(s,p,CM) ÷ GT(CM) | E25: 4 segments | F25: 59.6% / 9.8% / 7.6% / 23.0% | G25: (M(CM* / INSIGNIA / - / CA)+M(CM* / INSIGNIA / - / SA)+M(CM* / INSIGNIA / - / Deposits)+M(CM* / INSIGNIA / - / ODFD))/M(CM* / Grand Total) | H25: %
A26: 8 | B26: Mix & share | C26: Product share of GT | D26: Σs M(s,p,CM) ÷ GT(CM) | E26: 4 products | F26: 5.2% / 16.9% / 77.9% / 0.0% | G26: (M(CM* / INSIGNIA / - / CA)+M(CM* / SIGNATURE / - / CA)+M(CM* / ASPIRE / - / CA)+M(CM* / MASS / - / CA))/M(CM* / Grand Total) | H26: %
A27: 9 | B27: Mix & share | C27: CASA ratio | D27: CASA ÷ GT | E27: 6 period views | F27: CM 22.1%; LM 26.5%; LY 30.2% | G27: ((M(CM* / INSIGNIA / - / CA)+M(CM* / SIGNATURE / - / CA)+M(CM* / ASPIRE / - / CA)+M(CM* / MASS / - / CA))+(M(CM* / INSIGNIA / - / SA)+M(CM* / SIGNATURE / - / SA)+M(CM* / ASPIRE / - / SA)+M(CM* / MASS / - / SA)))/M(CM* / Grand Total) | H27: %
A28: 10 | B28: Mix & share | C28: < 3 Cr sub-book share | D28: sh3 = M < 3 Cr ÷ M | E28: 16 lines + roll-ups | F28: GT 55.5%; INSIGNIA 51.4%; MASS 44.5% | G28: M(CM 3 Cr* / Grand Total)/M(CM* / Grand Total) | H28: %
A29: 11 | B29: Mix & share | C29: Individual < 3 Cr share | D29: shI = M < 3 Ind Cr ÷ M | E29: 16 lines + roll-ups | F29: GT 38.5%; SA 73.4%; Deposits 33.2% | G29: M(CM 3 Ind Cr* / Grand Total)/M(CM* / Grand Total) | H29: %
A30: 12 | B30: Growth & momentum | C30: MoM growth | D30: g(LM) | E30: 16 lines + roll-ups | F30: GT +21.7%; segments +38.9% / +7.3% / +7.6% / -0.3% | G30: M(CM* / Grand Total)/M(LM* / Grand Total)-1 | H30: %
A31: 13 | B31: Growth & momentum | C31: YoY growth | D31: g(LY) | E31: 16 lines + roll-ups | F31: GT +38.9%; segments +74.6% / +20.2% / +17.2% / -0.8% | G31: M(CM* / Grand Total)/M(LY* / Grand Total)-1 | H31: %
A32: 14 | B32: Growth & momentum | C32: Growth vs LYCM basis | D32: g(LYCM) | E32: 16 lines + roll-ups | F32: GT +57.3%; products +11.1% / +9.3% / +79.3% / +87.6% | G32: M(CM* / Grand Total)/M(LYCM* / Grand Total)-1 | H32: %
... A43: 25 | B43: Data integrity | C43: LYCM definition flag | D43: LYCM* ≠ LY* | E43: Page | F43: LY minus LYCM Grand Total: 9,702.53 | G43: M(LY* / Grand Total)-M(LYCM* / Grand Total) | H43: Cr
A45: ⚠ DRAFT ONLY — Requires review and approval by a qualified Alvarez and Marsal professional before use.
